labssh/__init__.py
labssh/main.py
labssh/myssh.py
labssh-1.0.2.dist-info/METADATA
labssh-1.0.2.dist-info/WHEEL
labssh-1.0.2.dist-info/entry_points.txt
labssh-1.0.2.dist-info/top_level.txt
labssh-1.0.2.dist-info/RECORD
